gimapdev/ArrowRotateMap.png
gimapdev/ArrowRotateMapAll.png
gimapdev/GIBigmap_luma_0125x_pad125.png
gimapdev/GICityInner_05x.png
gimapdev/GICityOuter_05x.png
gimapdev/GIMAP.png
gimapdev/GIMAP_0125x.png
gimapdev/GIMAP_05x.png
gimapdev/GIMAP_luma_05x.png
gimapdev/GIReachableMask_0125x_pad125.png
gimapdev/__init__.py
gimapdev/__version__.py
gimapdev-4.6.3.dist-info/METADATA
gimapdev-4.6.3.dist-info/WHEEL
gimapdev-4.6.3.dist-info/RECORD
