Metadata-Version: 2.3
Name: gimapdev
Version: 4.6.3
Summary: gimap dev for GIA.
Author: Infstellar
Classifier: License :: OSI Approved :: MIT License
Classifier: Operating System :: OS Independent
Classifier: Programming Language :: Python :: 3
Requires-Python: >=3.7
